pmgr/CfgModel.py
pmgr/FreezeTableView.py
pmgr/MyDelegate.py
pmgr/ObjModel.py
pmgr/__init__.py
pmgr/__main__.py
pmgr/_version.py
pmgr/auth.ui
pmgr/cfgdialog.ui
pmgr/chown.ui
pmgr/colchoose.ui
pmgr/colmgr.py
pmgr/colsave.ui
pmgr/coluse.ui
pmgr/confirmdialog.ui
pmgr/db.py
pmgr/deriveddialog.ui
pmgr/dialogs.py
pmgr/docopt.py
pmgr/errordialog.ui
pmgr/param.py
pmgr/pmgr.py
pmgr/pmgr.ui
pmgr/pmgrAPI.py
pmgr/pmgrUtils.cfg
pmgr/pmgrUtils.py
pmgr/pmgrobj.py
pmgr/utils.py
pmgr/version.py
pmgr/DB/ims_motor.sql
pmgr/DB/ims_motor_cfg.sql
pmgr/DB/ims_motor_cfg_log.sql
pmgr/DB/ims_motor_log.sql
pmgr/DB/ims_motor_name_map.sql
pmgr/DB/ims_motor_update.sql
pmgr/DB/procs.sql
pmgr/tests/__init__.py
pmgr/tests/test_pmgr.py
pmgr-2.1.4.dist-info/licenses/AUTHORS.rst
pmgr-2.1.4.dist-info/licenses/LICENSE.md
pmgr-2.1.4.dist-info/METADATA
pmgr-2.1.4.dist-info/WHEEL
pmgr-2.1.4.dist-info/entry_points.txt
pmgr-2.1.4.dist-info/top_level.txt
pmgr-2.1.4.dist-info/RECORD
