Metadata-Version: 2.4
Name: pmgr
Version: 2.1.4
Summary: Parameter Manager for LCLS Device Configurations
Author: SLAC National Accelerator Laboratory
License: Copyright (c) 2023, The Board of Trustees of the Leland Stanford Junior
Classifier: Development Status :: 2 - Pre-Alpha
Classifier: Natural Language :: English
Classifier: Programming Language :: Python :: 3
Requires-Python: >=3.9
License-File: LICENSE.md
License-File: AUTHORS.rst
Requires-Dist: docopt
Requires-Dist: mysqlclient>=2.0.3
Requires-Dist: pcdsutils
Requires-Dist: pykerberos>=1.1.14
Requires-Dist: pyqt5
Provides-Extra: test
Requires-Dist: pytest; extra == "test"
Dynamic: license-file
